pafy/__init__.py
pafy/backend_internal.py
pafy/backend_shared.py
pafy/backend_youtube_dl.py
pafy/channel.py
pafy/g.py
pafy/jsinterp.py
pafy/pafy.py
pafy/playlist.py
pafy/util.py
pafy-0.5.4.data/scripts/ytdl
pafy-0.5.4.dist-info/DESCRIPTION.rst
pafy-0.5.4.dist-info/METADATA
pafy-0.5.4.dist-info/RECORD
pafy-0.5.4.dist-info/WHEEL
pafy-0.5.4.dist-info/metadata.json
pafy-0.5.4.dist-info/top_level.txt
